setup.cfg
setup.py
unix_dates/__init__.py
unix_dates/tests.py
unix_dates.egg-info/PKG-INFO
unix_dates.egg-info/SOURCES.txt
unix_dates.egg-info/dependency_links.txt
unix_dates.egg-info/top_level.txt