Metadata-Version: 1.0
Name: unix-dates
Version: 0.3
Summary: Python Unix Dates conversion utilities
Home-page: https://github.com/ophirh/python-unix-dates
Author: Ophir
Author-email: opensource@itculate.io
License: MIT
Keywords: unix,dates,utc,timestamp
Platform: UNKNOWN
